<annotation>
	<folder>VOC2007</folder>
	<filename>009935.jpg</filename>
	<source>
		<database>The VOC2007 Database</database>
		<annotation>PASCAL VOC2007</annotation>
		<image>flickr</image>
		<flickrid>329235518</flickrid>
	</source>
	<owner>
		<flickrid>Podulent</flickrid>
		<name>?</name>
	</owner>
	<size>
		<width>500</width>
		<height>375</height>
		<depth>3</depth>
	</size>
	<segmented>0</segmented>
	<object>
		<name>person</name>
		<pose>Right</pose>
		<truncated>1</truncated>
		<difficult>0</difficult>
		<bndbox>
			<xmin>274</xmin>
			<ymin>155</ymin>
			<xmax>436</xmax>
			<ymax>372</ymax>
		</bndbox>
	</object>
	<object>
		<name>person</name>
		<pose>Rear</pose>
		<truncated>1</truncated>
		<difficult>0</difficult>
		<bndbox>
			<xmin>104</xmin>
			<ymin>124</ymin>
			<xmax>179</xmax>
			<ymax>206</ymax>
		</bndbox>
	</object>
	<object>
		<name>person</name>
		<pose>Rear</pose>
		<truncated>1</truncated>
		<difficult>0</difficult>
		<bndbox>
			<xmin>1</xmin>
			<ymin>134</ymin>
			<xmax>73</xmax>
			<ymax>264</ymax>
		</bndbox>
	</object>
</annotation>
